airqtl/__init__.py
airqtl/__main__.py
airqtl/air.py
airqtl/association.py
airqtl/cov.py
airqtl/heritability.py
airqtl/kinship.py
airqtl/op.py
airqtl/sim.py
airqtl/pipeline/__init__.py
airqtl/pipeline/cgrn.py
airqtl/pipeline/dataset.py
airqtl/pipeline/eqtl.py
airqtl/pipeline/utils.py
airqtl/utils/__init__.py
airqtl/utils/eqtl.py
airqtl/utils/importing.py
airqtl/utils/numpy.py
airqtl/utils/qv.py
airqtl-1.0.0.dist-info/licenses/LICENSE
airqtl-1.0.0.dist-info/METADATA
airqtl-1.0.0.dist-info/WHEEL
airqtl-1.0.0.dist-info/entry_points.txt
airqtl-1.0.0.dist-info/top_level.txt
airqtl-1.0.0.dist-info/RECORD
