Metadata-Version: 2.4
Name: airqtl
Version: 1.0.0
Summary: Array of Interleaved Repeats for Quantitative Trait Loci
Author: Matthew Funk, Yuhe Wang
Author-email: Lingfei Wang <Lingfei.Wang.github@outlook.com>
License-Expression: BSD-3-Clause
Project-URL: Homepage, https://github.com/grnlab/airqtl
Project-URL: Issues, https://github.com/grnlab/airqtl/issues
Project-URL: Repository, https://github.com/grnlab/airqtl.git
Keywords: qtl,eqtl,scqtl,sceqtl,lmm,quantitative trait loci,expression quantitative trait loci,single-cell quantitative trait loci,single-cell expression quantitative trait loci,linear mixed model,linear mixed models,population-scale scRNA-seq,gene regulatory network,network inference,causal inference,mendelian randomization
Classifier: Development Status :: 5 - Production/Stable
Classifier: Environment :: Console
Classifier: Environment :: GPU :: NVIDIA CUDA
Classifier: Framework :: Pytest
Classifier: Intended Audience :: Science/Research
Classifier: Intended Audience :: Developers
Classifier: Intended Audience :: Education
Classifier: Operating System :: OS Independent
Classifier: Programming Language :: Python :: 3
Classifier: Topic :: Scientific/Engineering :: Bio-Informatics
Requires-Python: >=3.12
License-File: LICENSE
Requires-Dist: numpy
Requires-Dist: h5py
Requires-Dist: scipy
Requires-Dist: pandas
Requires-Dist: networkx
Requires-Dist: torch>=2.0
Requires-Dist: scikit-learn
Requires-Dist: lz4
Requires-Dist: normalisr
Requires-Dist: docstring2argparse
Requires-Dist: snakemake
Dynamic: license-file
